gonk/__init__.py
gonk/api/__init__.py
gonk/api/server.py
gonk/core/__init__.py
gonk/core/events.py
gonk/core/exceptions.py
gonk/core/integrity.py
gonk/core/interfaces.py
gonk/core/validators.py
gonk/impl/fs.py
gonk/impl/sq3.py
gonk_ai-0.1.4.dist-info/LICENSE
gonk_ai-0.1.4.dist-info/METADATA
gonk_ai-0.1.4.dist-info/WHEEL
gonk_ai-0.1.4.dist-info/entry_points.txt
gonk_ai-0.1.4.dist-info/top_level.txt
gonk_ai-0.1.4.dist-info/RECORD
