Metadata-Version: 2.1
Name: gonk-ai
Version: 0.1.4
Summary: Generic backend for dataset annotation.
Author-email: TACIXAT <douglas@computeheavy.com>
Project-URL: Homepage, https://github.com/ComputeHeavy/gonk
Project-URL: Bug Tracker, https://github.com/ComputeHeavy/gonk/issues
Classifier: Programming Language :: Python :: 3
Classifier: License :: OSI Approved :: GNU Affero General Public License v3
Classifier: Operating System :: OS Independent
Classifier: Topic :: Scientific/Engineering :: Artificial Intelligence
Classifier: Intended Audience :: Science/Research
Requires-Python: >=3.11
License-File: LICENSE
Requires-Dist: Flask
Requires-Dist: jsonschema
Requires-Dist: PyNaCl
Requires-Dist: click
Requires-Dist: requests
